dexsensor.cpython-311-x86_64-linux-gnu.so
dexsensor.build/.gitignore
dexsensor-0.3.1.dist-info/METADATA
dexsensor-0.3.1.dist-info/WHEEL
dexsensor-0.3.1.dist-info/entry_points.txt
dexsensor-0.3.1.dist-info/top_level.txt
dexsensor-0.3.1.dist-info/RECORD
dexsensor-0.3.1.dist-info/licenses/LICENSE
