Metadata-Version: 2.4
Name: dexsensor
Version: 0.3.1
Summary: A Python library for processing sensor data on Dexmate Robots
Author-email: Dexmate <contact@dexmate.ai>
Keywords: robot,robotics,sensors,camera,imu,python
Classifier: Programming Language :: Python :: 3
Classifier: Programming Language :: Python :: 3.10
Classifier: Programming Language :: Python :: 3.11
Classifier: Programming Language :: Python :: 3.12
Classifier: Programming Language :: Python :: 3.13
Classifier: Operating System :: OS Independent
Classifier: Typing :: Typed
Requires-Python: <3.14,>=3.10
License-File: LICENSE
Requires-Dist: numpy>=2.2.1
Requires-Dist: hydra-core>=1.3.2
Requires-Dist: omegaconf>=2.3.0
Requires-Dist: loguru>=0.7.3
Requires-Dist: tyro>=0.9.24
Requires-Dist: colorama>=0.4.6
Requires-Dist: pyserial>=3.5
Requires-Dist: scipy>=1.15.0
Requires-Dist: pyrplidarsdk>=0.1.0
Requires-Dist: opencv-python>=4.8.0
Requires-Dist: dexcomm>=0.1.17
Requires-Dist: aiortc>=1.6.0
Requires-Dist: websockets>=11.0
Requires-Dist: aiofiles>=23.0.0
Requires-Dist: uvloop>=0.17.0
Requires-Dist: av>=14.4.0
Dynamic: license-file
